sg_otio/__init__.py
sg_otio/clip_group.py
sg_otio/command.py
sg_otio/constants.py
sg_otio/cut_clip.py
sg_otio/cut_diff.py
sg_otio/media_cutter.py
sg_otio/media_uploader.py
sg_otio/plugin_manifest.json
sg_otio/sg_cut_reader.py
sg_otio/sg_cut_track_writer.py
sg_otio/sg_settings.py
sg_otio/track_diff.py
sg_otio/utils.py
sg_otio/adapters/__init__.py
sg_otio/adapters/cmx_3600.py
sg_otio/adapters/shotgrid.py
sg_otio-1.1.13.data/scripts/sg-otio
sg_otio-1.1.13.data/scripts/sg-otio.py
tests/__init__.py
tests/conftest.py
tests/test_clip_group.py
tests/test_command.py
tests/test_cut_clip.py
tests/test_cut_diff.py
tests/test_media_cutter.py
tests/test_media_uploader.py
tests/test_shotgrid_adapter.py
tests/test_utils.py
tests/python/__init__.py
tests/python/mock_grid.py
tests/python/sg_test.py
sg_otio-1.1.13.dist-info/LICENSE.txt
sg_otio-1.1.13.dist-info/METADATA
sg_otio-1.1.13.dist-info/WHEEL
sg_otio-1.1.13.dist-info/entry_points.txt
sg_otio-1.1.13.dist-info/top_level.txt
sg_otio-1.1.13.dist-info/RECORD
