Metadata-Version: 2.1
Name: sg-otio
Version: 1.1.13
Summary: A library for OpenTimelineIO integration with ShotGrid
Home-page: https://github.com/GPLgithub/sg-otio.git
Author: GPL Technologies
Author-email: pipelinesupport@gpltech.com
License: Apache License 2.0
Classifier: Development Status :: 4 - Beta
Classifier: Intended Audience :: Developers
Classifier: Topic :: Multimedia :: Video
Classifier: Topic :: Multimedia :: Video :: Display
Classifier: Topic :: Multimedia :: Video :: Non-Linear Editor
Classifier: Topic :: Software Development :: Libraries :: Python Modules
Classifier: Programming Language :: Python :: 3
Classifier: Programming Language :: Python :: 3.7
Classifier: Programming Language :: Python :: 3.8
Classifier: Programming Language :: Python :: 3.9
Classifier: Programming Language :: Python :: 3.10
Classifier: Operating System :: OS Independent
Classifier: License :: OSI Approved :: MIT License
Classifier: Natural Language :: English
License-File: LICENSE.txt
Requires-Dist: OpenTimelineIO==0.16.0
Requires-Dist: shotgun-api3>=3.3.3
Requires-Dist: futures; python_version < "3.2"
Requires-Dist: pathlib2; python_version < "3.4"
Provides-Extra: dev
Requires-Dist: flake8; extra == "dev"
Requires-Dist: pytest; extra == "dev"
Requires-Dist: pytest-cov; extra == "dev"
Requires-Dist: twine; extra == "dev"
